httpmock/__init__.py
httpmock/py.typed
httpmock-0.1.0.dist-info/LICENSE
httpmock-0.1.0.dist-info/METADATA
httpmock-0.1.0.dist-info/WHEEL
httpmock-0.1.0.dist-info/RECORD
