Metadata-Version: 2.1
Name: httpmock
Version: 0.1.0
Summary: Fluent API for mocking HTTP requests in Python tests
Home-page: https://github.com/thehale/httpmock
License: MPL-2.0
Keywords: test,mock,http,httpretty
Author: Joseph Hale
Author-email: me@jhale.dev
Requires-Python: >=3.8,<4.0
Classifier: License :: OSI Approved
Classifier: Programming Language :: Python :: 3
Classifier: Programming Language :: Python :: 3.8
Classifier: Programming Language :: Python :: 3.9
Classifier: Programming Language :: Python :: 3.10
Classifier: Programming Language :: Python :: 3.11
Classifier: Programming Language :: Python :: 3.12
Requires-Dist: httpretty (>=1.1.4,<2.0.0)
Project-URL: Documentation, https://github.com/thehale/httpmock
Project-URL: Repository, https://github.com/thehale/httpmock
